security_checker/__init__.py
security_checker/cli.py
security_checker/console.py
security_checker/checkers/__init__.py
security_checker/checkers/_base.py
security_checker/checkers/_models.py
security_checker/checkers/_settings.py
security_checker/checkers/credentials/_models.py
security_checker/checkers/credentials/_vendor_trait.py
security_checker/checkers/credentials/credentials.py
security_checker/checkers/licenses/_known_licenses.py
security_checker/checkers/licenses/_models.py
security_checker/checkers/licenses/_settings.py
security_checker/checkers/licenses/_vendor_trait.py
security_checker/checkers/licenses/licenses.py
security_checker/checkers/vulnerabilities/_models.py
security_checker/checkers/vulnerabilities/_settings.py
security_checker/checkers/vulnerabilities/_vendor_trait.py
security_checker/checkers/vulnerabilities/vulnerabilities.py
security_checker/notifiers/_base.py
security_checker/notifiers/markdown.py
security_checker/notifiers/slack.py
security_checker/notifiers/stdout.py
security_checker/utils/git.py
security_checker/utils/text.py
security_checker/vendors/_base.py
security_checker/vendors/_models.py
security_checker/vendors/npm.py
security_checker/vendors/pnpm.py
security_checker/vendors/poetry.py
security_checker/vendors/requirements_txt.py
security_checker/vendors/rye.py
security_checker/vendors/yarn.py
security_checker/vendors/registries/github_security_advisory.py
security_checker/vendors/registries/npm.py
security_checker/vendors/registries/pypi.py
security_checker-0.2.3.dist-info/METADATA
security_checker-0.2.3.dist-info/WHEEL
security_checker-0.2.3.dist-info/entry_points.txt
security_checker-0.2.3.dist-info/RECORD
