Metadata-Version: 2.3
Name: security-checker
Version: 0.2.3
Summary: A comprehensive command-line tool to check security-related issues in your projects, including vulnerability scanning and license compliance checking.
Project-URL: Homepage, https://github.com/Ja-sonYun/security-checker
Project-URL: Repository, https://github.com/Ja-sonYun/security-checker.git
Project-URL: Issues, https://github.com/Ja-sonYun/security-checker/issues
Author-email: Ja-sonYun <killa30867@gmail.com>
License: MIT
Keywords: compliance,dependencies,license,scanning,security,vulnerability
Classifier: Development Status :: 4 - Beta
Classifier: Intended Audience :: Developers
Classifier: License :: OSI Approved :: MIT License
Classifier: Operating System :: OS Independent
Classifier: Programming Language :: Python :: 3
Classifier: Programming Language :: Python :: 3.10
Classifier: Programming Language :: Python :: 3.11
Classifier: Programming Language :: Python :: 3.12
Classifier: Programming Language :: Python :: 3.13
Classifier: Topic :: Security
Classifier: Topic :: Software Development :: Quality Assurance
Classifier: Topic :: System :: Systems Administration
Requires-Python: >=3.10
Requires-Dist: aiohttp>=3.12.12
Requires-Dist: gitpython>=3.1.44
Requires-Dist: httpx>=0.28.1
Requires-Dist: openai>=1.86.0
Requires-Dist: packaging>=25.0
Requires-Dist: pydantic-argparse>=0.10.0
Requires-Dist: pydantic-settings>=2.9.1
Requires-Dist: pydantic>=2.11.5
Requires-Dist: pyyaml>=6.0.2
Requires-Dist: rich>=14.0.0
Requires-Dist: semantic-version>=2.10.0
Requires-Dist: slack-sdk>=3.35.0
Requires-Dist: tenacity>=9.1.2
